LICENSE.txt
MANIFEST.in
setup.py
TrashPandas/__init__.py
TrashPandas/levels.py
TrashPandas/main.py
TrashPandas/scoreboard.py
TrashPandas/units.py
TrashPandas/window.py
TrashPandasPiervn.egg-info/PKG-INFO
TrashPandasPiervn.egg-info/SOURCES.txt
TrashPandasPiervn.egg-info/dependency_links.txt
TrashPandasPiervn.egg-info/entry_points.txt
TrashPandasPiervn.egg-info/not-zip-safe
TrashPandasPiervn.egg-info/requires.txt
TrashPandasPiervn.egg-info/top_level.txt
assets/background_lvl1_blur.jpg
assets/background_lvl2_blur.jpg
assets/bullet_fire.png
assets/heart_32.png
assets/racoon64.png
assets/spaceshipv2.png