Metadata-Version: 2.1
Name: TrashPandasPiervn
Version: 1.0.2
Summary: Simple game written with pygame.
Home-page: UNKNOWN
Author: Aleksander Łopusiewicz
Author-email: oleklopusiewicz@gmail.com
License: MIT
Keywords: TrashPandas
Platform: UNKNOWN
Classifier: Programming Language :: Python :: 3
Classifier: License :: OSI Approved :: MIT License
Classifier: Operating System :: OS Independent
License-File: LICENSE.txt
